LICENSE
MANIFEST.in
README.rst
setup.cfg
setup.py
django_mailauth.egg-info/PKG-INFO
django_mailauth.egg-info/SOURCES.txt
django_mailauth.egg-info/dependency_links.txt
django_mailauth.egg-info/top_level.txt
docs/.gitkeep
mailauth/__init__.py
mailauth/admin.py
mailauth/apps.py
mailauth/forms.py
mailauth/managers.py
mailauth/models.py
mailauth/views.py
mailauth/management/__init__.py
mailauth/management/commands/__init__.py
mailauth/management/commands/defaultsuperuser.py
mailauth/migrations/__init__.py
mailauth/tests/__init__.py
mailauth/tests/test_managers.py